dler/__init__.py
dler/__version__.py
dler/cli/__init__.py
dler/cli/main.py
dler/constants.py
dler/context.py
dler/dler.py
dler/downloaders.py
dler/enums.py
dler/loggers.py
dler/models.py
dler/tasker/__init__.py
dler/tasker/base.py
dler/tasker/exceptions.py
dler/tasker/file_tasker.py
dler/tasker/m3u8_tasker.py
dler/tasker/models.py
dler/tasker/tasktools.py
dler/tasker/video_tasker.py
dler-0.6.0.dist-info/entry_points.txt
dler-0.6.0.dist-info/LICENSE
dler-0.6.0.dist-info/WHEEL
dler-0.6.0.dist-info/METADATA
dler-0.6.0.dist-info/RECORD
