Metadata-Version: 2.1
Name: dler
Version: 0.6.0
Summary: python video downloader
License: MIT
Author: wxnacy
Author-email: 371032668@qq.com
Requires-Python: >=3.9,<4.0
Classifier: License :: OSI Approved :: MIT License
Classifier: Programming Language :: Python :: 3
Classifier: Programming Language :: Python :: 3.10
Classifier: Programming Language :: Python :: 3.9
Requires-Dist: m3u8 (>=2.0.0,<3.0.0)
Requires-Dist: multitasker (>=0.0.7,<0.0.8)
Requires-Dist: requests (>=2.27.1,<3.0.0)
Requires-Dist: typer (>=0.4.1,<0.5.0)
Requires-Dist: wsco (>=0.0.1,<0.0.2)
